folderplay/__init__.py
folderplay/__main__.py
folderplay/__version__.py
folderplay/config.py
folderplay/constants.py
folderplay/localplayer.py
folderplay/media.py
folderplay/player.py
folderplay/utils.py
folderplay/assets/fonts/Roboto/Roboto-Regular.ttf
folderplay/assets/icons/icon.ico
folderplay/assets/icons/feather/check_box.svg
folderplay/assets/icons/feather/check_box_blank.svg
folderplay/assets/icons/feather/clock.svg
folderplay/assets/icons/feather/copy.svg
folderplay/assets/icons/feather/delete_forever.svg
folderplay/assets/icons/feather/folder.svg
folderplay/assets/icons/feather/folder_open.svg
folderplay/assets/icons/feather/monitor.svg
folderplay/assets/icons/feather/movie.svg
folderplay/assets/icons/feather/play.svg
folderplay/assets/icons/feather/play_circle.svg
folderplay/assets/icons/feather/refresh.svg
folderplay/assets/icons/feather/settings.svg
folderplay/assets/icons/feather/size.svg
folderplay/assets/icons/feather/visibility.svg
folderplay/assets/icons/feather/visibility_off.svg
folderplay/assets/icons/material/check_box.svg
folderplay/assets/icons/material/check_box_blank.svg
folderplay/assets/icons/material/clock.svg
folderplay/assets/icons/material/copy.svg
folderplay/assets/icons/material/delete_forever.svg
folderplay/assets/icons/material/folder.svg
folderplay/assets/icons/material/folder_open.svg
folderplay/assets/icons/material/monitor.svg
folderplay/assets/icons/material/movie.svg
folderplay/assets/icons/material/play.svg
folderplay/assets/icons/material/play_circle.svg
folderplay/assets/icons/material/refresh.svg
folderplay/assets/icons/material/settings.svg
folderplay/assets/icons/material/size.svg
folderplay/assets/icons/material/visibility.svg
folderplay/assets/icons/material/visibility_off.svg
folderplay/assets/styles/frameless.qss
folderplay/assets/styles/qtmodern.qss
folderplay/gui/__init__.py
folderplay/gui/basicviewwidget.py
folderplay/gui/button.py
folderplay/gui/groupbox.py
folderplay/gui/icons.py
folderplay/gui/label.py
folderplay-0.4.3.dist-info/LICENSE
folderplay-0.4.3.dist-info/METADATA
folderplay-0.4.3.dist-info/WHEEL
folderplay-0.4.3.dist-info/entry_points.txt
folderplay-0.4.3.dist-info/top_level.txt
folderplay-0.4.3.dist-info/RECORD
