Metadata-Version: 2.1
Name: folderplay
Version: 0.4.3
Summary: Remember watched tv episodes, resume from where you left off
Home-page: https://github.com/hurlenko/folderplay
Author: Hurlenko
License: MIT
Project-URL: Source, https://github.com/hurlenko/folderplay
Platform: UNKNOWN
Classifier: License :: OSI Approved :: MIT License
Classifier: Programming Language :: Python
Classifier: Programming Language :: Python :: 3.5
Classifier: Programming Language :: Python :: 3.6
Classifier: Programming Language :: Python :: 3.7
Classifier: Programming Language :: Python :: 3.8
Classifier: Programming Language :: Python :: Implementation :: CPython
Requires-Python: >=3.5
Requires-Dist: Click (==7.0)
Requires-Dist: pymediainfo (==4.0)
Requires-Dist: PyQt5 (==5.13.1)
